radio_beam/__init__.py
radio_beam/_astropy_init.py
radio_beam/beam.py
radio_beam/commonbeam.py
radio_beam/conftest.py
radio_beam/multiple_beams.py
radio_beam/utils.py
radio_beam/version.py
radio_beam/tests/__init__.py
radio_beam/tests/setup_package.py
radio_beam/tests/test_beam.py
radio_beam/tests/test_beams.py
radio_beam/tests/test_kernels.py
radio_beam/tests/data/NGC0925.bima.mmom0.fits.gz
radio_beam/tests/data/NGC0925.bima.mmom0.image.tar.gz
radio_beam/tests/data/generate_commonbeam_table.py
radio_beam/tests/data/header_aips.hdr
radio_beam/tests/data/header_jybeam.hdr
radio_beam/tests/data/m33_beams_bintable.fits.gz
radio_beam/tests/data/m83.moment0.fits.gz
radio_beam/tests/data/ngc0925_na.fits.gz
radio_beam-0.3.8.dist-info/LICENSE.rst
radio_beam-0.3.8.dist-info/METADATA
radio_beam-0.3.8.dist-info/WHEEL
radio_beam-0.3.8.dist-info/top_level.txt
radio_beam-0.3.8.dist-info/RECORD
