Metadata-Version: 2.1
Name: radio-beam
Version: 0.3.8
Summary: Operations for radio astronomy beams with astropy
Home-page: http://radio_beam.readthedocs.org
Author: Adam Leroy, Adam Ginsburg, Erik Rosolowsky, Tom Robitaille, and Eric Koch
Author-email: adam.g.ginsburg@gmail.com, koch.eric.w@gmail.com
License: BSD
License-File: LICENSE.rst
Requires-Dist: astropy
Requires-Dist: numpy>=1.8.0
Requires-Dist: scipy
Provides-Extra: test
Requires-Dist: pytest-astropy; extra == "test"
Requires-Dist: pytest-cov; extra == "test"
Requires-Dist: matplotlib; extra == "test"
Provides-Extra: docs
Requires-Dist: sphinx-astropy; extra == "docs"
Requires-Dist: matplotlib; extra == "docs"
Provides-Extra: all
Requires-Dist: scipy; extra == "all"
Requires-Dist: matplotlib; extra == "all"
